django_persian_pdf/__init__.py
django_persian_pdf/apps.py
django_persian_pdf/compilers.py
django_persian_pdf/py.typed
django_persian_pdf/responses.py
django_persian_pdf/views.py
django_persian_pdf-0.1.3.dist-info/LICENSE
django_persian_pdf-0.1.3.dist-info/METADATA
django_persian_pdf-0.1.3.dist-info/WHEEL
django_persian_pdf-0.1.3.dist-info/top_level.txt
django_persian_pdf-0.1.3.dist-info/RECORD
