Metadata-Version: 2.1
Name: django-persian-pdf
Version: 0.1.3
Summary: Django class based views to generate pdf files using html or latex template.
Author-email: Ali Abharya <abharya.dev@gmail.com>
Maintainer-email: Ali Abharya <abharya.dev@gmail.com>
License: MIT
Project-URL: Changelog, https://github.com/bindruid/django-persian-pdf/blob/master/CHANGELOG.rst
Project-URL: Repository, https://github.com/bindruid/django-persian-pdf
Keywords: pdf,django,persian,xelatex
Classifier: Development Status :: 3 - Alpha
Classifier: Environment :: Web Environment
Classifier: Framework :: Django
Classifier: Framework :: Django :: 3.2
Classifier: Framework :: Django :: 4.0
Classifier: Framework :: Django :: 4.1
Classifier: Framework :: Django :: 4.2
Classifier: Framework :: Django :: 5.0
Classifier: Intended Audience :: Developers
Classifier: License :: OSI Approved :: MIT License
Classifier: Natural Language :: English
Classifier: Operating System :: OS Independent
Classifier: Programming Language :: Python :: 3 :: Only
Classifier: Programming Language :: Python :: 3.10
Classifier: Programming Language :: Python :: 3.11
Classifier: Programming Language :: Python :: 3.12
Classifier: Programming Language :: Python :: Implementation :: CPython
Classifier: Typing :: Typed
Requires-Python: >=3.10
License-File: LICENSE
Requires-Dist: Django >=3.2
